{
  "lastUpdatedAt": "2026-03-08T23:22:26.244Z",
  "microgonsInCirculation": "641373733718n",
  "micronotsInCirculation": "1013396049885n",
  "usdForArgon": 1.03,
  "usdForArgonot": 1,
  "usdForBtc": 66270.999,
  "mining": {
    "activeSeatCount": 100,
    "activeBidCosts": 0,
    "activeBlockRewards": 100954.08977281272,
    "activeAPY": null
  },
  "vaulting": {
    "count": 19,
    "valueInVaults": 8015.904642522761,
    "bitcoinLocked": 0.12095635,
    "epochEarnings": 27669.942412653356,
    "argonBurnCapacity": 3117587.3162740935,
    "activeAPY": 4.2407242395125045e+35
  }
}