{
  "lastUpdatedAt": "2026-02-10T05:03:06.356Z",
  "microgonsInCirculation": "546343635218n",
  "micronotsInCirculation": "916984658385n",
  "usdForArgon": 1.026,
  "usdForArgonot": 1,
  "usdForBtc": 69772.8,
  "mining": {
    "activeSeatCount": 100,
    "activeBidCosts": 0,
    "activeBlockRewards": 95132.44645814224,
    "activeAPY": null
  },
  "vaulting": {
    "count": 19,
    "valueInVaults": 8439.470744609904,
    "bitcoinLocked": 0.12095635,
    "epochEarnings": 27562.48858573982,
    "argonBurnCapacity": 3295100.2059488953,
    "activeAPY": 4.2407242395125045e+35
  }
}