{
  "lastUpdatedAt": "2026-03-09T14:09:41.959Z",
  "microgonsInCirculation": "643936737218n",
  "micronotsInCirculation": "1015992746385n",
  "usdForArgon": 1.03,
  "usdForArgonot": 1,
  "usdForBtc": 68767.65,
  "mining": {
    "activeSeatCount": 100,
    "activeBidCosts": 0,
    "activeBlockRewards": 101161.73794100773,
    "activeAPY": null
  },
  "vaulting": {
    "count": 19,
    "valueInVaults": 8317.89067880145,
    "bitcoinLocked": 0.12095635,
    "epochEarnings": 27669.942412653356,
    "argonBurnCapacity": 3235037.2958309897,
    "activeAPY": 4.2407242395125045e+35
  }
}