{
  "lastUpdatedAt": "2026-07-12T21:07:31.516Z",
  "currentBlockNumber": 867091,
  "baseMicrogonsMinedPerBlock": "3672750n",
  "baseMicronotsMinedPerBlock": "3681000n",
  "microgonsInCirculation": "1211728396001n",
  "micronotsInCirculation": "1571418575885n",
  "usdForArgon": 1.047,
  "usdTargetForArgon": 1.049,
  "usdForArgonot": 0.157,
  "usdForBtc": 73494.795,
  "restabilizationLeverage": 7,
  "miningAPR": 618.2,
  "vaultingAPR": 2.844018137403427,
  "bondsAPR": 0,
  "bitcoinAPR": 13.754055078455597,
  "mining": {
    "activeSeatCount": 100,
    "activeBidCosts": 0,
    "activeBlockRewards": 82289.09488003625
  },
  "vaulting": {
    "count": 19,
    "valueInVaults": 22134.391209162393,
    "bitcoinLocked": 0.30116924,
    "bitcoinTxnCount": 19,
    "epochEarnings": 0,
    "argonBurnCapacity": 8452929.220136479
  }
}