{
  "lastUpdatedAt": "2026-02-25T08:45:44.028Z",
  "microgonsInCirculation": "593748976718n",
  "micronotsInCirculation": "965154018135n",
  "usdForArgon": 1.03,
  "usdForArgonot": 1,
  "usdForBtc": 65436.874,
  "mining": {
    "activeSeatCount": 100,
    "activeBidCosts": 0,
    "activeBlockRewards": 98669.95992266753,
    "activeAPY": null
  },
  "vaulting": {
    "count": 19,
    "valueInVaults": 7915.011845009594,
    "bitcoinLocked": 0.12095635,
    "epochEarnings": 27669.942412653356,
    "argonBurnCapacity": 3078347.5648227255,
    "activeAPY": 4.2407242395125045e+35
  }
}